finbrain_mcp/__init__.py
finbrain_mcp/auth.py
finbrain_mcp/client_adapter.py
finbrain_mcp/registry.py
finbrain_mcp/server.py
finbrain_mcp/utils.py
finbrain_mcp/normalizers/__init__.py
finbrain_mcp/normalizers/analyst_ratings.py
finbrain_mcp/normalizers/app_ratings.py
finbrain_mcp/normalizers/availability.py
finbrain_mcp/normalizers/house_trades.py
finbrain_mcp/normalizers/insider_transactions.py
finbrain_mcp/normalizers/linkedin.py
finbrain_mcp/normalizers/options.py
finbrain_mcp/normalizers/predictions.py
finbrain_mcp/normalizers/senate_trades.py
finbrain_mcp/normalizers/sentiments.py
finbrain_mcp/normalizers/shared.py
finbrain_mcp/tools/analyst_ratings.py
finbrain_mcp/tools/app_ratings.py
finbrain_mcp/tools/availability.py
finbrain_mcp/tools/health.py
finbrain_mcp/tools/house_trades.py
finbrain_mcp/tools/insider_transactions.py
finbrain_mcp/tools/linkedin.py
finbrain_mcp/tools/options.py
finbrain_mcp/tools/predictions.py
finbrain_mcp/tools/senate_trades.py
finbrain_mcp/tools/sentiments.py
finbrain_mcp-0.1.6.dist-info/licenses/LICENSE
finbrain_mcp-0.1.6.dist-info/METADATA
finbrain_mcp-0.1.6.dist-info/WHEEL
finbrain_mcp-0.1.6.dist-info/entry_points.txt
finbrain_mcp-0.1.6.dist-info/top_level.txt
finbrain_mcp-0.1.6.dist-info/RECORD
