Metadata-Version: 2.4
Name: finbrain-mcp
Version: 0.1.6
Summary: Open-source FinBrain MCP server (SDK-first via finbrain-python)
Author-email: Ahmet Salim Bilgin <ahmet@finbrain.tech>
License-Expression: MIT
Requires-Python: >=3.10
License-File: LICENSE
Requires-Dist: fastmcp>=2
Requires-Dist: pydantic>=2
Requires-Dist: finbrain-python>=0.1.0
Provides-Extra: http
Requires-Dist: requests>=2; extra == "http"
Requires-Dist: pandas>=2; extra == "http"
Provides-Extra: dev
Requires-Dist: pytest>=8; extra == "dev"
Requires-Dist: pytest-cov>=5; extra == "dev"
Requires-Dist: ruff>=0.5; extra == "dev"
Requires-Dist: mypy>=1.10; extra == "dev"
Requires-Dist: build>=1.2; extra == "dev"
Requires-Dist: pandas-stubs>=2.2.2.240603; extra == "dev"
Dynamic: license-file
